finetune_lab/__init__.py
finetune_lab/client.py
finetune_lab/loader.py
finetune_lab/training_predictions.py
finetune_lab/trainers/__init__.py
finetune_lab/trainers/dpo_trainer.py
finetune_lab/trainers/rlhf_trainer.py
finetune_lab/trainers/sft_trainer.py
finetune_lab-0.6.0.dist-info/METADATA
finetune_lab-0.6.0.dist-info/WHEEL
finetune_lab-0.6.0.dist-info/entry_points.txt
finetune_lab-0.6.0.dist-info/top_level.txt
finetune_lab-0.6.0.dist-info/RECORD
