Metadata-Version: 2.4
Name: finetune-lab
Version: 0.6.0
Summary: FineTune Lab SDK - Training, inference, batch testing, and analytics for LLMs
Home-page: https://github.com/finetune-lab/python-sdk
Author: FineTune Lab Team
Author-email: support@finetunelab.com
Classifier: Development Status :: 3 - Alpha
Classifier: Intended Audience :: Developers
Classifier: Intended Audience :: Science/Research
Classifier: Topic :: Scientific/Engineering :: Artificial Intelligence
Classifier: License :: OSI Approved :: MIT License
Classifier: Programming Language :: Python :: 3
Classifier: Programming Language :: Python :: 3.8
Classifier: Programming Language :: Python :: 3.9
Classifier: Programming Language :: Python :: 3.10
Classifier: Programming Language :: Python :: 3.11
Requires-Python: >=3.8
Requires-Dist: requests>=2.31.0
Provides-Extra: training
Requires-Dist: transformers>=4.35.0; extra == "training"
Requires-Dist: torch>=2.0.0; extra == "training"
Requires-Dist: datasets>=2.14.0; extra == "training"
Requires-Dist: peft>=0.6.0; extra == "training"
Requires-Dist: accelerate>=0.24.0; extra == "training"
Requires-Dist: bitsandbytes>=0.41.0; extra == "training"
Requires-Dist: trl>=0.7.0; extra == "training"
Provides-Extra: dev
Requires-Dist: pytest>=7.0; extra == "dev"
Requires-Dist: black>=23.0; extra == "dev"
Requires-Dist: flake8>=6.0; extra == "dev"
Dynamic: author
Dynamic: author-email
Dynamic: classifier
Dynamic: description
Dynamic: description-content-type
Dynamic: home-page
Dynamic: provides-extra
Dynamic: requires-dist
Dynamic: requires-python
Dynamic: summary
